README.md
setup.cfg
setup.py
Goog_API/Goog_API.py
Goog_API/Goog_API_Calendar_Metodos.py
Goog_API/Goog_API_Docs_Metodos.py
Goog_API/Goog_API_Drive_Metodos.py
Goog_API/Goog_API_Sheets_Metodos.py
Goog_API/Goog_API_gMail_Metodos.py
Goog_API.egg-info/PKG-INFO
Goog_API.egg-info/SOURCES.txt
Goog_API.egg-info/dependency_links.txt
Goog_API.egg-info/requires.txt
Goog_API.egg-info/top_level.txt