Metadata-Version: 2.1
Name: Goog-API
Version: 0.22
Summary: Librería Python con métodos para las APIs de Google. Docs, Sheets, Drive, Gmail y Calendar. Desarrollada por Hernán A. Teszkiewicz Novick, para el equipo dev. de Ch'aska.
Home-page: https://github.com/Chaska-de-ideas/Goog_API
Author: Hernán A. Teszkiewicz Novick
Author-email: herni@cajadeideas.ar
License: MIT
Download-URL: https://github.com/Chaska-de-ideas/Goog_API/raw/main/dist/Goog_API-0.22.tar.gz
Platform: UNKNOWN
Provides-Extra: Goog_API_gMail_Metodos
Provides-Extra: Goog_API_Calendar_Metodos
Provides-Extra: Goog_API_Sheets_Metodos
